[
    {
        "id": "seed-1",
        "name": "Civil Hospital Ahmedabad",
        "city": "Ahmedabad",
        "address": "B.J. Medical College, Asarwa, Ahmedabad-380016",
        "contact_phone": "079-22683721",
        "emergency_phone": "108",
        "type": "Government",
        "blood_bank_available": true,
        "blood_bank_name": "Department of IHBT",
        "blood_bank_contact": "9825097675",
        "latitude": 23.0362,
        "longitude": 72.6004,
        "email": null,
        "website": null,
        "beds": 2400,
        "specialties": [
            "General",
            "Trauma",
            "Emergency",
            "Obstetrics"
        ]
    },
    {
        "id": "seed-2",
        "name": "GMERS Medical College & Hospital Sola",
        "city": "Ahmedabad",
        "address": "Sola, Ahmedabad-380051",
        "contact_phone": "079-27680061",
        "emergency_phone": "079-27680062",
        "type": "Government",
        "blood_bank_available": true,
        "blood_bank_name": "GMERS Blood Bank",
        "blood_bank_contact": "9725327369",
        "latitude": 23.0727,
        "longitude": 72.5145,
        "email": "deangmerssola@gmail.com",
        "website": null,
        "beds": 650,
        "specialties": [
            "General",
            "Emergency",
            "Surgery"
        ]
    },
    {
        "id": "seed-3",
        "name": "V.S. Hospital",
        "city": "Ahmedabad",
        "address": "Ellisbridge, Ahmedabad-380006",
        "contact_phone": "079-26577621",
        "emergency_phone": "079-26577621",
        "type": "Government",
        "blood_bank_available": true,
        "blood_bank_name": "VS Hospital Blood Bank",
        "blood_bank_contact": "9328075500",
        "latitude": 23.0300,
        "longitude": 72.5620,
        "email": null,
        "website": null,
        "beds": 600,
        "specialties": [
            "General",
            "Emergency",
            "Orthopedics"
        ]
    },
    {
        "id": "seed-4",
        "name": "L.G. Hospital",
        "city": "Ahmedabad",
        "address": "Maninagar, Ahmedabad-380008",
        "contact_phone": "079-25461200",
        "emergency_phone": "079-25461200",
        "type": "Government",
        "blood_bank_available": true,
        "blood_bank_name": "LG Hospital Blood Centre",
        "blood_bank_contact": "7567802565",
        "latitude": 22.9973,
        "longitude": 72.6022,
        "email": null,
        "website": null,
        "beds": 450,
        "specialties": [
            "General",
            "Obstetrics",
            "Pediatrics"
        ]
    },
    {
        "id": "seed-5",
        "name": "Sterling Hospital",
        "city": "Ahmedabad",
        "address": "Drive In Road, Memnagar, Ahmedabad-380052",
        "contact_phone": "079-40011111",
        "emergency_phone": "079-40011111",
        "type": "Private",
        "blood_bank_available": true,
        "blood_bank_name": "Sterling Blood Bank",
        "blood_bank_contact": "9723430962",
        "latitude": 23.0435,
        "longitude": 72.5287,
        "email": "info@sterlinghospitals.com",
        "website": "https://sterlinghospitals.com",
        "beds": 350,
        "specialties": [
            "Cardiology",
            "Neurology",
            "Oncology",
            "Orthopedics"
        ]
    },
    {
        "id": "seed-6",
        "name": "Gujarat Cancer Research Institute",
        "city": "Ahmedabad",
        "address": "Civil Hospital Campus, Asarwa, Ahmedabad-380016",
        "contact_phone": "079-22687011",
        "emergency_phone": "079-22687011",
        "type": "Government",
        "blood_bank_available": true,
        "blood_bank_name": "GCRI Blood Bank",
        "blood_bank_contact": "9723382841",
        "latitude": 23.0370,
        "longitude": 72.6008,
        "email": null,
        "website": "https://gcriindia.org",
        "beds": 700,
        "specialties": [
            "Oncology",
            "Cancer Surgery",
            "Radiotherapy"
        ]
    },
    {
        "id": "seed-7",
        "name": "IKDRC - Institute of Kidney Diseases",
        "city": "Ahmedabad",
        "address": "Manjushree Mill Compound, Asarwa, Ahmedabad",
        "contact_phone": "079-22685011",
        "emergency_phone": "079-22685011",
        "type": "Government",
        "blood_bank_available": true,
        "blood_bank_name": "IKDRC Blood Bank",
        "blood_bank_contact": "9662539914",
        "latitude": 23.0380,
        "longitude": 72.5980,
        "email": null,
        "website": "https://ikdrc.org",
        "beds": 350,
        "specialties": [
            "Nephrology",
            "Kidney Transplant",
            "Dialysis"
        ]
    },
    {
        "id": "seed-8",
        "name": "Apollo Hospitals",
        "city": "Gandhinagar",
        "address": "Plot No. 1A, GIDC Bhat, Gandhinagar-Ahmedabad Road, Gandhinagar-382428",
        "contact_phone": "079-66701800",
        "emergency_phone": "1066",
        "type": "Private",
        "blood_bank_available": true,
        "blood_bank_name": "Apollo Blood Bank",
        "blood_bank_contact": "079-66701800",
        "latitude": 23.1100,
        "longitude": 72.6261,
        "email": "apolloahd@apollohospitals.com",
        "website": "https://apollohospitals.com",
        "beds": 289,
        "specialties": [
            "Cardiology",
            "Neurology",
            "Oncology",
            "Transplant"
        ]
    },
    {
        "id": "seed-9",
        "name": "KD Hospital",
        "city": "Gandhinagar",
        "address": "Vaishnodevi Circle, SG Highway, Ahmedabad-382421",
        "contact_phone": "079-66770000",
        "emergency_phone": "079-66770001",
        "type": "Private",
        "blood_bank_available": true,
        "blood_bank_name": "KD Hospital Blood Bank",
        "blood_bank_contact": "079-66770000",
        "latitude": 23.1352,
        "longitude": 72.5414,
        "email": "info@kdhospital.co.in",
        "website": "https://kdhospital.co.in",
        "beds": 350,
        "specialties": [
            "Cardiology",
            "Orthopedics",
            "Neurology",
            "Emergency"
        ]
    },
    {
        "id": "seed-10",
        "name": "GMERS Medical College Hospital Gandhinagar",
        "city": "Gandhinagar",
        "address": "Civil Hospital Campus, Sector-12, Gandhinagar-382012",
        "contact_phone": "079-23240296",
        "emergency_phone": "079-23221931",
        "type": "Government",
        "blood_bank_available": true,
        "blood_bank_name": "GMERS Blood Bank",
        "blood_bank_contact": "079-23240296",
        "latitude": 23.2150,
        "longitude": 72.6360,
        "email": "deangmersmcg@gmail.com",
        "website": "https://gmersmchgandhinagar.com",
        "beds": 500,
        "specialties": [
            "General",
            "Emergency",
            "Surgery",
            "Obstetrics"
        ]
    },
    {
        "id": "seed-11",
        "name": "New Civil Hospital Surat",
        "city": "Surat",
        "address": "Majura Gate, Surat-395001",
        "contact_phone": "0261-2244456",
        "emergency_phone": "0261-2244456",
        "type": "Government",
        "blood_bank_available": true,
        "blood_bank_name": "Civil Hospital Blood Bank",
        "blood_bank_contact": "0261-2244456",
        "latitude": 21.1950,
        "longitude": 72.8310,
        "email": null,
        "website": null,
        "beds": 1200,
        "specialties": [
            "General",
            "Trauma",
            "Emergency",
            "Obstetrics"
        ]
    },
    {
        "id": "seed-12",
        "name": "SMIMER Hospital",
        "city": "Surat",
        "address": "Umarwada, Bombay Market, Surat-395010",
        "contact_phone": "0261-2452455",
        "emergency_phone": "0261-2452455",
        "type": "Government",
        "blood_bank_available": true,
        "blood_bank_name": "SMIMER Blood Bank",
        "blood_bank_contact": "0261-2452455",
        "latitude": 21.1857,
        "longitude": 72.8214,
        "email": null,
        "website": null,
        "beds": 700,
        "specialties": [
            "General",
            "Emergency",
            "Medical Education"
        ]
    },
    {
        "id": "seed-13",
        "name": "Surat Raktadan Kendra",
        "city": "Surat",
        "address": "Gopipura, Surat-395001",
        "contact_phone": "0261-2417754",
        "emergency_phone": "0261-2630114",
        "type": "Specialty",
        "blood_bank_available": true,
        "blood_bank_name": "Surat Raktadan Kendra",
        "blood_bank_contact": "0261-2630114",
        "latitude": 21.1920,
        "longitude": 72.8260,
        "email": null,
        "website": null,
        "beds": null,
        "specialties": [
            "Blood Bank",
            "Blood Donation"
        ]
    },
    {
        "id": "seed-14",
        "name": "Kiran Hospital",
        "city": "Surat",
        "address": "Katargam, Surat-395004",
        "contact_phone": "0261-2531000",
        "emergency_phone": "0261-2531000",
        "type": "Private",
        "blood_bank_available": true,
        "blood_bank_name": "Kiran Blood Bank",
        "blood_bank_contact": "0261-2531000",
        "latitude": 21.2250,
        "longitude": 72.8080,
        "email": "info@kiranhospital.com",
        "website": "https://kiranhospital.com",
        "beds": 500,
        "specialties": [
            "Cardiology",
            "Neurology",
            "Orthopedics",
            "Oncology"
        ]
    },
    {
        "id": "seed-15",
        "name": "S.S.G. Hospital Vadodara",
        "city": "Vadodara",
        "address": "Jail Road, Vadodara-390001",
        "contact_phone": "0265-2424848",
        "emergency_phone": "0265-2424848",
        "type": "Government",
        "blood_bank_available": true,
        "blood_bank_name": "SSG Blood Bank",
        "blood_bank_contact": "0265-2424848",
        "latitude": 22.3050,
        "longitude": 73.1920,
        "email": null,
        "website": null,
        "beds": 1500,
        "specialties": [
            "General",
            "Trauma",
            "Emergency",
            "Surgery"
        ]
    },
    {
        "id": "seed-16",
        "name": "Bhailal Amin General Hospital",
        "city": "Vadodara",
        "address": "Alembic Road, Subhanpura, Vadodara-390003",
        "contact_phone": "0265-2281301",
        "emergency_phone": "0265-2281301",
        "type": "Private",
        "blood_bank_available": true,
        "blood_bank_name": "BAGH Blood Bank",
        "blood_bank_contact": "0265-2281301",
        "latitude": 22.3120,
        "longitude": 73.1730,
        "email": null,
        "website": "https://bagh.org.in",
        "beds": 450,
        "specialties": [
            "Cardiology",
            "Orthopedics",
            "General Surgery"
        ]
    },
    {
        "id": "seed-17",
        "name": "Jamanabai General Hospital",
        "city": "Vadodara",
        "address": "Mandvi, Vadodara-390001",
        "contact_phone": "0265-2511740",
        "emergency_phone": "0265-2511740",
        "type": "Government",
        "blood_bank_available": true,
        "blood_bank_name": "Jamanabai Blood Bank",
        "blood_bank_contact": "0265-2511740",
        "latitude": 22.2980,
        "longitude": 73.1960,
        "email": null,
        "website": null,
        "beds": 400,
        "specialties": [
            "General",
            "Obstetrics",
            "Pediatrics"
        ]
    },
    {
        "id": "seed-18",
        "name": "Sterling Hospital Vadodara",
        "city": "Vadodara",
        "address": "Race Course, Vadodara-390007",
        "contact_phone": "0265-4003456",
        "emergency_phone": "0265-4003456",
        "type": "Private",
        "blood_bank_available": true,
        "blood_bank_name": "Sterling Blood Bank",
        "blood_bank_contact": "0265-4003456",
        "latitude": 22.3200,
        "longitude": 73.1850,
        "email": "info@sterlinghospitals.com",
        "website": "https://sterlinghospitals.com",
        "beds": 300,
        "specialties": [
            "Cardiology",
            "Neurology",
            "Orthopedics"
        ]
    },
    {
        "id": "seed-19",
        "name": "HCG Cancer Centre Rajkot",
        "city": "Rajkot",
        "address": "Near Ayodhya Chowk, 150 Ft Ring Road, Rajkot-360005",
        "contact_phone": "0281-6358888817",
        "emergency_phone": "0281-6358888817",
        "type": "Private",
        "blood_bank_available": true,
        "blood_bank_name": "HCG Blood Bank",
        "blood_bank_contact": "0281-6358888817",
        "latitude": 22.3195,
        "longitude": 70.7737,
        "email": null,
        "website": "https://hcghospitals.in",
        "beds": 200,
        "specialties": [
            "Oncology",
            "Cardiology",
            "Neurology"
        ]
    },
    {
        "id": "seed-20",
        "name": "P.D.U. Medical College Hospital",
        "city": "Rajkot",
        "address": "Bhakti Nagar, Rajkot-360005",
        "contact_phone": "0281-2473030",
        "emergency_phone": "0281-2473030",
        "type": "Government",
        "blood_bank_available": true,
        "blood_bank_name": "PDU Blood Bank",
        "blood_bank_contact": "0281-2473030",
        "latitude": 22.3082,
        "longitude": 70.8007,
        "email": null,
        "website": null,
        "beds": 800,
        "specialties": [
            "General",
            "Trauma",
            "Emergency",
            "Medical Education"
        ]
    },
    {
        "id": "seed-21",
        "name": "Gokul Superspeciality Hospital",
        "city": "Rajkot",
        "address": "12/14 Manhar Plot, Vidhyanagar Main Road, Rajkot-360002",
        "contact_phone": "099043-99043",
        "emergency_phone": "079001-08108",
        "type": "Private",
        "blood_bank_available": true,
        "blood_bank_name": "Gokul Blood Bank",
        "blood_bank_contact": "099043-99043",
        "latitude": 22.2970,
        "longitude": 70.7830,
        "email": null,
        "website": "https://gokulhospital.com",
        "beds": 300,
        "specialties": [
            "Cardiology",
            "Neurology",
            "Orthopedics",
            "Emergency"
        ]
    },
    {
        "id": "seed-22",
        "name": "Life Blood Centre Rajkot",
        "city": "Rajkot",
        "address": "24, Malaviya Nagar Main Road, Opp. Arya Samaj, Bhakti Nagar, Rajkot-360002",
        "contact_phone": "0281-2234242",
        "emergency_phone": "0281-2234242",
        "type": "Specialty",
        "blood_bank_available": true,
        "blood_bank_name": "Life Blood Centre",
        "blood_bank_contact": "0281-2234242",
        "latitude": 22.2990,
        "longitude": 70.7900,
        "email": null,
        "website": "https://life4life.org.in",
        "beds": null,
        "specialties": [
            "Blood Bank",
            "Blood Donation",
            "Research"
        ]
    },
    {
        "id": "seed-23",
        "name": "Sir T Hospital (Sir Takhtasinhji Hospital)",
        "city": "Bhavnagar",
        "address": "Jail Road, Kalanala, Bhavnagar-364001",
        "contact_phone": "0278-2423131",
        "emergency_phone": "0278-2423131",
        "type": "Government",
        "blood_bank_available": true,
        "blood_bank_name": "Sir T Blood Bank",
        "blood_bank_contact": "0278-2423131",
        "latitude": 21.7628,
        "longitude": 72.1533,
        "email": null,
        "website": null,
        "beds": 700,
        "specialties": [
            "General",
            "Trauma",
            "Emergency",
            "Medical Education"
        ]
    },
    {
        "id": "seed-24",
        "name": "HCG Hospital Bhavnagar",
        "city": "Bhavnagar",
        "address": "1139 Sir Patani Road, Krishna Nagar, Meghani Circle, Bhavnagar-364001",
        "contact_phone": "0278-6640108",
        "emergency_phone": "0278-6640111",
        "type": "Private",
        "blood_bank_available": true,
        "blood_bank_name": "HCG Blood Bank",
        "blood_bank_contact": "0278-6640108",
        "latitude": 21.7745,
        "longitude": 72.1525,
        "email": null,
        "website": "https://hcghospitals.in",
        "beds": 150,
        "specialties": [
            "Oncology",
            "Cardiology",
            "Neurology"
        ]
    },
    {
        "id": "seed-25",
        "name": "Bhavnagar Blood Bank",
        "city": "Bhavnagar",
        "address": "Sardarnagar Circle, Sardarnagar, Bhavnagar-364001",
        "contact_phone": "0278-2561526",
        "emergency_phone": "9825207660",
        "type": "Specialty",
        "blood_bank_available": true,
        "blood_bank_name": "Bhavnagar Blood Bank",
        "blood_bank_contact": "9825207660",
        "latitude": 21.7700,
        "longitude": 72.1480,
        "email": "bhavnagarbloodbank@yahoo.co.in",
        "website": null,
        "beds": null,
        "specialties": [
            "Blood Bank",
            "Blood Donation"
        ]
    },
    {
        "id": "seed-26",
        "name": "G.G. Hospital Jamnagar",
        "city": "Jamnagar",
        "address": "Pandit Nehru Marg, Near M.P. Shah Medical College, Jamnagar-361008",
        "contact_phone": "0288-2553191",
        "emergency_phone": "0288-2553191",
        "type": "Government",
        "blood_bank_available": true,
        "blood_bank_name": "GG Hospital Blood Bank",
        "blood_bank_contact": "0288-2553191",
        "latitude": 22.4729,
        "longitude": 70.0667,
        "email": null,
        "website": null,
        "beds": 850,
        "specialties": [
            "General",
            "Trauma",
            "Emergency",
            "Medical Education"
        ]
    },
    {
        "id": "seed-27",
        "name": "Oshwal Aayush Super Speciality Hospital",
        "city": "Jamnagar",
        "address": "Digvijay Plot, Opposite Police Station, Jamnagar-361005",
        "contact_phone": "0288-2554949",
        "emergency_phone": "0288-2554949",
        "type": "Private",
        "blood_bank_available": true,
        "blood_bank_name": "Oshwal Blood Bank",
        "blood_bank_contact": "0288-2554949",
        "latitude": 22.4680,
        "longitude": 70.0600,
        "email": null,
        "website": null,
        "beds": 200,
        "specialties": [
            "Cardiology",
            "Orthopedics",
            "Gastroenterology",
            "Urology"
        ]
    },
    {
        "id": "seed-28",
        "name": "Jamnagar Voluntary Blood Bank",
        "city": "Jamnagar",
        "address": "First Floor, Shankuntal Apartment, Hawai Chowk, Jamnagar",
        "contact_phone": "0288-2673339",
        "emergency_phone": "0288-2541070",
        "type": "Specialty",
        "blood_bank_available": true,
        "blood_bank_name": "Jamnagar Voluntary Blood Bank",
        "blood_bank_contact": "0288-2673339",
        "latitude": 22.4710,
        "longitude": 70.0580,
        "email": null,
        "website": null,
        "beds": null,
        "specialties": [
            "Blood Bank",
            "Blood Donation"
        ]
    },
    {
        "id": "seed-29",
        "name": "Anand Agricultural University Hospital",
        "city": "Anand",
        "address": "Anand-388110",
        "contact_phone": "02692-261571",
        "emergency_phone": "02692-261571",
        "type": "Government",
        "blood_bank_available": false,
        "blood_bank_name": null,
        "blood_bank_contact": null,
        "latitude": 22.5645,
        "longitude": 72.9289,
        "email": null,
        "website": null,
        "beds": 100,
        "specialties": [
            "General",
            "Primary Care"
        ]
    },
    {
        "id": "seed-30",
        "name": "Shree Krishna Hospital",
        "city": "Anand",
        "address": "Gokalnagar, Karamsad, Anand-388325",
        "contact_phone": "02692-228222",
        "emergency_phone": "02692-228222",
        "type": "Private",
        "blood_bank_available": true,
        "blood_bank_name": "Shree Krishna Blood Bank",
        "blood_bank_contact": "02692-228222",
        "latitude": 22.5380,
        "longitude": 72.9050,
        "email": null,
        "website": "https://pschmc.org",
        "beds": 800,
        "specialties": [
            "General",
            "Cardiology",
            "Orthopedics",
            "Medical Education"
        ]
    },
    {
        "id": "seed-31",
        "name": "Bhuj Civil Hospital",
        "city": "Bhuj",
        "address": "Hospital Road, Bhuj, Kutch-370001",
        "contact_phone": "02832-220121",
        "emergency_phone": "02832-220121",
        "type": "Government",
        "blood_bank_available": true,
        "blood_bank_name": "Bhuj Civil Blood Bank",
        "blood_bank_contact": "02832-220121",
        "latitude": 23.2420,
        "longitude": 69.6669,
        "email": null,
        "website": null,
        "beds": 500,
        "specialties": [
            "General",
            "Trauma",
            "Emergency"
        ]
    },
    {
        "id": "seed-32",
        "name": "Mandvi General Hospital",
        "city": "Bhuj",
        "address": "Mandvi, Kutch-370465",
        "contact_phone": "02834-223241",
        "emergency_phone": "02834-223241",
        "type": "Government",
        "blood_bank_available": false,
        "blood_bank_name": null,
        "blood_bank_contact": null,
        "latitude": 22.8330,
        "longitude": 69.3520,
        "email": null,
        "website": null,
        "beds": 150,
        "specialties": [
            "General",
            "Primary Care"
        ]
    },
    {
        "id": "seed-33",
        "name": "Civil Hospital Mehsana",
        "city": "Mehsana",
        "address": "Kadi Road, Mehsana-384001",
        "contact_phone": "02762-252291",
        "emergency_phone": "02762-252291",
        "type": "Government",
        "blood_bank_available": true,
        "blood_bank_name": "Mehsana Civil Blood Bank",
        "blood_bank_contact": "02762-252291",
        "latitude": 23.5880,
        "longitude": 72.3693,
        "email": null,
        "website": null,
        "beds": 400,
        "specialties": [
            "General",
            "Emergency",
            "Surgery"
        ]
    },
    {
        "id": "seed-34",
        "name": "GMERS Medical College Mehsana",
        "city": "Mehsana",
        "address": "Gozariya Highway, Mehsana-384001",
        "contact_phone": "02762-243001",
        "emergency_phone": "02762-243001",
        "type": "Government",
        "blood_bank_available": true,
        "blood_bank_name": "GMERS Blood Bank",
        "blood_bank_contact": "02762-243001",
        "latitude": 23.5950,
        "longitude": 72.3800,
        "email": null,
        "website": null,
        "beds": 500,
        "specialties": [
            "General",
            "Medical Education",
            "Emergency"
        ]
    },
    {
        "id": "seed-35",
        "name": "Nadiad Civil Hospital",
        "city": "Nadiad",
        "address": "College Road, Nadiad-387001",
        "contact_phone": "0268-2521188",
        "emergency_phone": "0268-2521188",
        "type": "Government",
        "blood_bank_available": true,
        "blood_bank_name": "Nadiad Civil Blood Bank",
        "blood_bank_contact": "0268-2521188",
        "latitude": 22.6916,
        "longitude": 72.8634,
        "email": null,
        "website": null,
        "beds": 350,
        "specialties": [
            "General",
            "Emergency",
            "Surgery"
        ]
    },
    {
        "id": "seed-36",
        "name": "Dhiraj Hospital",
        "city": "Nadiad",
        "address": "Piparia, Vadodara-Ahmedabad Road, Nadiad",
        "contact_phone": "02268-200300",
        "emergency_phone": "02268-200300",
        "type": "Private",
        "blood_bank_available": true,
        "blood_bank_name": "Dhiraj Blood Bank",
        "blood_bank_contact": "02268-200300",
        "latitude": 22.6800,
        "longitude": 72.8500,
        "email": null,
        "website": "https://sbunivsity.edu.in",
        "beds": 1200,
        "specialties": [
            "Cardiology",
            "Orthopedics",
            "Neurology",
            "Oncology"
        ]
    },
    {
        "id": "seed-37",
        "name": "Junagadh Civil Hospital",
        "city": "Junagadh",
        "address": "Civil Hospital Road, Junagadh-362001",
        "contact_phone": "0285-2621533",
        "emergency_phone": "0285-2621533",
        "type": "Government",
        "blood_bank_available": true,
        "blood_bank_name": "Junagadh Civil Blood Bank",
        "blood_bank_contact": "0285-2621533",
        "latitude": 21.5222,
        "longitude": 70.4579,
        "email": null,
        "website": null,
        "beds": 500,
        "specialties": [
            "General",
            "Emergency",
            "Trauma"
        ]
    },
    {
        "id": "seed-38",
        "name": "Morbi General Hospital",
        "city": "Morbi",
        "address": "Hospital Road, Morbi-363641",
        "contact_phone": "02822-222241",
        "emergency_phone": "02822-222241",
        "type": "Government",
        "blood_bank_available": true,
        "blood_bank_name": "Morbi Blood Bank",
        "blood_bank_contact": "02822-222241",
        "latitude": 22.8173,
        "longitude": 70.8378,
        "email": null,
        "website": null,
        "beds": 300,
        "specialties": [
            "General",
            "Emergency"
        ]
    },
    {
        "id": "seed-39",
        "name": "Patan Civil Hospital",
        "city": "Patan",
        "address": "Station Road, Patan-384265",
        "contact_phone": "02766-222222",
        "emergency_phone": "02766-222222",
        "type": "Government",
        "blood_bank_available": true,
        "blood_bank_name": "Patan Civil Blood Bank",
        "blood_bank_contact": "02766-222222",
        "latitude": 23.8493,
        "longitude": 72.1266,
        "email": null,
        "website": null,
        "beds": 300,
        "specialties": [
            "General",
            "Emergency"
        ]
    },
    {
        "id": "seed-40",
        "name": "Valsad Civil Hospital",
        "city": "Valsad",
        "address": "Civil Hospital Road, Valsad-396001",
        "contact_phone": "02632-243515",
        "emergency_phone": "02632-243515",
        "type": "Government",
        "blood_bank_available": true,
        "blood_bank_name": "Valsad Civil Blood Bank",
        "blood_bank_contact": "02632-243515",
        "latitude": 20.5992,
        "longitude": 72.9342,
        "email": null,
        "website": null,
        "beds": 350,
        "specialties": [
            "General",
            "Emergency",
            "Surgery"
        ]
    },
    {
        "id": "seed-41",
        "name": "Indian Red Cross Society Ahmedabad",
        "city": "Ahmedabad",
        "address": "Navrangpura, Near Navrang Circle, Ahmedabad",
        "contact_phone": "079-26564627",
        "emergency_phone": "9099917781",
        "type": "Specialty",
        "blood_bank_available": true,
        "blood_bank_name": "Red Cross Blood Centre Ahmedabad",
        "blood_bank_contact": "9099917781",
        "latitude": 23.0365,
        "longitude": 72.5560,
        "email": null,
        "website": "https://indianredcross.org",
        "beds": null,
        "specialties": [
            "Blood Bank",
            "Blood Donation",
            "Disaster Relief"
        ]
    },
    {
        "id": "seed-42",
        "name": "Indian Red Cross Society Vadodara",
        "city": "Vadodara",
        "address": "Siddhi Vinayak Complex, Opp. Platform No.6, Railway Station, Alkapuri, Vadodara",
        "contact_phone": "0265-2321616",
        "emergency_phone": "0265-2321616",
        "type": "Specialty",
        "blood_bank_available": true,
        "blood_bank_name": "Red Cross Blood Centre Vadodara",
        "blood_bank_contact": "0265-2321616",
        "latitude": 22.3100,
        "longitude": 73.1810,
        "email": null,
        "website": "https://indianredcross.org",
        "beds": null,
        "specialties": [
            "Blood Bank",
            "Blood Donation"
        ]
    },
    {
        "id": "seed-43",
        "name": "Indian Red Cross Society Bhavnagar",
        "city": "Bhavnagar",
        "address": "Divanpara Road, Diwanpara, Bhavnagar-364001",
        "contact_phone": "0278-2424040",
        "emergency_phone": "0278-2424040",
        "type": "Specialty",
        "blood_bank_available": true,
        "blood_bank_name": "Red Cross Blood Centre Bhavnagar",
        "blood_bank_contact": "0278-2424040",
        "latitude": 21.7720,
        "longitude": 72.1550,
        "email": null,
        "website": "https://indianredcross.org",
        "beds": null,
        "specialties": [
            "Blood Bank",
            "Blood Donation"
        ]
    },
    {
        "id": "seed-44",
        "name": "Indu Voluntary Blood Bank",
        "city": "Vadodara",
        "address": "Vinraj Plaza, Opp. Government Press, Kothi, Vadodara-390001",
        "contact_phone": "0265-2437676",
        "emergency_phone": "0265-2411477",
        "type": "Specialty",
        "blood_bank_available": true,
        "blood_bank_name": "Indu Voluntary Blood Bank",
        "blood_bank_contact": "0265-2437676",
        "latitude": 22.3040,
        "longitude": 73.1890,
        "email": null,
        "website": null,
        "beds": null,
        "specialties": [
            "Blood Bank",
            "Blood Donation"
        ]
    },
    {
        "id": "seed-45",
        "name": "Zydus Hospital Ahmedabad",
        "city": "Ahmedabad",
        "address": "Thaltej, SG Highway, Ahmedabad-380054",
        "contact_phone": "079-66190200",
        "emergency_phone": "079-66190200",
        "type": "Private",
        "blood_bank_available": true,
        "blood_bank_name": "Zydus Blood Bank",
        "blood_bank_contact": "079-66190200",
        "latitude": 23.0450,
        "longitude": 72.5018,
        "email": "info@zydushospitals.com",
        "website": "https://zydushospitals.com",
        "beds": 450,
        "specialties": [
            "Cardiology",
            "Oncology",
            "Neurology",
            "Transplant"
        ]
    }
]